LICENSE.txt
setup.py
Pylines_tx.egg-info/PKG-INFO
Pylines_tx.egg-info/SOURCES.txt
Pylines_tx.egg-info/dependency_links.txt
Pylines_tx.egg-info/top_level.txt
code/__init__.py