Metadata-Version: 2.1
Name: Pylines-tx
Version: 0.1
Summary: library storage and management in txt files by-rows
Home-page: UNKNOWN
Author: youssef-khaled
License: UNKNOWN
Platform: UNKNOWN
Classifier: Programming Language :: Python :: 3.10
Classifier: License :: OSI Approved :: MIT License
License-File: LICENSE.txt
